{"data":{"propertyOrder":{},"properties":{"id":{"name":"id","reference":"scalar","primary":true,"type":"uuid","array":false},"user_id":{"name":"user_id","reference":"scalar","getter":false,"setter":false,"type":"string","array":false},"transactions":{"name":"transactions","reference":"1:m","cascade":["persist"],"type":"Transaction","array":true},"created_at":{"name":"created_at","reference":"scalar","getter":false,"setter":false,"type":"Date","array":false}},"props":[{"name":"id","reference":"scalar","primary":true,"type":"uuid","array":false},{"name":"user_id","reference":"scalar","getter":false,"setter":false,"type":"string","array":false},{"name":"transactions","reference":"1:m","cascade":["persist"],"type":"Transaction","array":true},{"name":"created_at","reference":"scalar","getter":false,"setter":false,"type":"Date","array":false}],"primaryKeys":["id"],"filters":{},"hooks":{},"indexes":[],"uniques":[],"checks":[],"concurrencyCheckKeys":{},"className":"Account","path":"./src/entities/account.entity.ts","name":"Account","abstract":false,"constructorParams":[],"toJsonParams":[],"useCache":true,"compositePK":false,"simplePK":true,"relations":[{"name":"transactions","reference":"1:m","cascade":["persist"],"type":"Transaction","array":true}],"collection":"account"},"origin":"./src/entities/account.entity.ts","hash":"839418cf3636c0a7607b28fb7a6e1a6c","version":"5.7.14"}
